{
  "cars": [
     {
      "id": 1,
      "Brand": "Tata",
			"Type":"Manual",
      "Year": 2021,
      "kms": 10000,
      "Description": "Tata Altroz with all original documents",
      "Price": 500000
    },
    {
      "id":2,
      "Brand": "Tata",
			"Type":"AMT",
      "Year": 2022,
      "kms": 8000,
      "Description": "Tata Nexon with all original documents",
      "Price": 800000
    },
    {
      "id":3,
      "Brand": "Tata",
      "Type":"Manual",
      "Year": 2021,
      "kms": 4000,
      "Description": "Tata Safari with all original documents",
      "Price": 900000
    }
  ],

  "wishlisted_cars": []
}